AUTHORS.md
CHANGELOG.md
CONTRIBUTING.md
LICENSE
MANIFEST.in
README.md
setup.py
openbases/__init__.py
openbases/version.py
openbases.egg-info/PKG-INFO
openbases.egg-info/SOURCES.txt
openbases.egg-info/dependency_links.txt
openbases.egg-info/entry_points.txt
openbases.egg-info/not-zip-safe
openbases.egg-info/requires.txt
openbases.egg-info/top_level.txt
openbases/cli/__init__.py
openbases/cli/badges/__init__.py
openbases/cli/badges/create.py
openbases/cli/badges/view.py
openbases/cli/icons/__init__.py
openbases/cli/papers/__init__.py
openbases/cli/papers/get.py
openbases/cli/papers/shell.py
openbases/cli/validate/__init__.py
openbases/cli/validate/paper.py
openbases/logger/__init__.py
openbases/logger/message.py
openbases/logger/progress.py
openbases/logger/spinner.py
openbases/main/__init__.py
openbases/main/defaults.py
openbases/main/icons.py
openbases/main/badges/__init__.py
openbases/main/base/Dockerfile
openbases/main/base/README.md
openbases/main/base/__init__.py
openbases/main/base/command.py
openbases/main/base/flags.py
openbases/main/base/generate.py
openbases/main/base/logger.py
openbases/main/papers/__init__.py
openbases/main/papers/tests.py
openbases/main/validate/__init__.py
openbases/main/validate/helpers.py
openbases/main/validate/criteria/base.py
openbases/main/validate/criteria/dummy.yml
openbases/main/validate/criteria/paper.yml
openbases/utils/__init__.py
openbases/utils/fileio.py
openbases/utils/managers.py
openbases/utils/terminal.py
openbases/utils/web.py
tests/__init__.py
tests/test_badges.py
tests/test_icons.py
tests/test_papers.py
tests/test_validator.py
tests/paper/paper.bib
tests/paper/paper.md