Metadata-Version: 2.1
Name: openbases
Version: 0.0.55
Summary: openbases python helper functions for https://openbases.github.io
Home-page: http://www.github.com/openbases/openbases-python
Author: Vanessa Sochat
Author-email: vsochat@stanford.edu
Maintainer: Vanessa Sochat
Maintainer-email: vsochat@stanford.edu
License: LICENSE
Keywords: openbases,markdown,pandoc
Platform: UNKNOWN
Classifier: Intended Audience :: Science/Research
Classifier: Intended Audience :: Developers
Classifier: Programming Language :: Python
Classifier: Topic :: Software Development
Classifier: Topic :: Scientific/Engineering
Classifier: Operating System :: Unix
Classifier: Programming Language :: Python :: 2.7
Classifier: Programming Language :: Python :: 3
Provides-Extra: validate
Provides-Extra: test
Provides-Extra: all
